awswrangler/__init__.py
awswrangler/__metadata__.py
awswrangler/_arrow.py
awswrangler/_config.py
awswrangler/_data_types.py
awswrangler/_databases.py
awswrangler/_distributed.py
awswrangler/_executor.py
awswrangler/_sql_formatter.py
awswrangler/_sql_utils.py
awswrangler/_utils.py
awswrangler/annotations.py
awswrangler/athena/__init__.py
awswrangler/athena/_cache.py
awswrangler/athena/_executions.py
awswrangler/athena/_executions.pyi
awswrangler/athena/_read.py
awswrangler/athena/_read.pyi
awswrangler/athena/_spark.py
awswrangler/athena/_statements.py
awswrangler/athena/_utils.py
awswrangler/athena/_write_iceberg.py
awswrangler/catalog/__init__.py
awswrangler/catalog/_add.py
awswrangler/catalog/_create.py
awswrangler/catalog/_definitions.py
awswrangler/catalog/_delete.py
awswrangler/catalog/_get.py
awswrangler/catalog/_utils.py
awswrangler/chime.py
awswrangler/cleanrooms/__init__.py
awswrangler/cleanrooms/_read.py
awswrangler/cleanrooms/_utils.py
awswrangler/cloudwatch.py
awswrangler/data_api/__init__.py
awswrangler/data_api/_connector.py
awswrangler/data_api/rds.py
awswrangler/data_api/redshift.py
awswrangler/data_quality/__init__.py
awswrangler/data_quality/_create.py
awswrangler/data_quality/_get.py
awswrangler/data_quality/_utils.py
awswrangler/distributed/__init__.py
awswrangler/distributed/ray/__init__.py
awswrangler/distributed/ray/_core.py
awswrangler/distributed/ray/_core.pyi
awswrangler/distributed/ray/_executor.py
awswrangler/distributed/ray/_register.py
awswrangler/distributed/ray/_utils.py
awswrangler/distributed/ray/datasources/__init__.py
awswrangler/distributed/ray/datasources/arrow_csv_datasink.py
awswrangler/distributed/ray/datasources/arrow_csv_datasource.py
awswrangler/distributed/ray/datasources/arrow_json_datasource.py
awswrangler/distributed/ray/datasources/arrow_orc_datasink.py
awswrangler/distributed/ray/datasources/arrow_orc_datasource.py
awswrangler/distributed/ray/datasources/arrow_parquet_base_datasource.py
awswrangler-3.11.0.dist-info/LICENSE.txt
awswrangler-3.11.0.dist-info/METADATA
awswrangler-3.11.0.dist-info/NOTICE.txt
awswrangler-3.11.0.dist-info/WHEEL
awswrangler-3.11.0.dist-info/RECORD
