Metadata-Version: 2.1
Name: awswrangler
Version: 3.11.0
Summary: Pandas on AWS.
Home-page: https://aws-sdk-pandas.readthedocs.io/
License: Apache-2.0
Keywords: pandas,aws
Author: Amazon Web Services
Requires-Python: >=3.9,<4.0
Classifier: License :: OSI Approved :: Apache Software License
Classifier: Programming Language :: Python :: 3
Classifier: Programming Language :: Python :: 3.9
Classifier: Programming Language :: Python :: 3.10
Classifier: Programming Language :: Python :: 3.11
Classifier: Programming Language :: Python :: 3.12
Classifier: Programming Language :: Python :: 3.13
Provides-Extra: deltalake
Provides-Extra: geopandas
Provides-Extra: gremlin
Provides-Extra: modin
Provides-Extra: mysql
Provides-Extra: opencypher
Provides-Extra: openpyxl
Provides-Extra: opensearch
Provides-Extra: oracle
Provides-Extra: postgres
Provides-Extra: progressbar
Provides-Extra: ray
Provides-Extra: redshift
Provides-Extra: sparql
Provides-Extra: sqlserver
Requires-Dist: SPARQLWrapper (>=2.0.0,<3.0.0) ; extra == "sparql"
Requires-Dist: aiohttp (>=3.9.0,<4.0.0) ; extra == "gremlin"
Requires-Dist: async-timeout (>=4.0.3,<6.0.0) ; extra == "gremlin"
Requires-Dist: boto3 (>=1.20.32,<2.0.0)
Requires-Dist: botocore (>=1.23.32,<2.0.0)
Requires-Dist: deltalake (>=0.18.0,<0.24.0) ; extra == "deltalake"
Requires-Dist: geopandas (>=0.13.2,<0.14.0) ; (python_version < "3.12") and (extra == "geopandas")
Requires-Dist: geopandas (>=0.14.1,<0.15.0) ; (python_version >= "3.12") and (extra == "geopandas")
Requires-Dist: gremlinpython (>=3.7.1,<4.0.0) ; extra == "gremlin"
Requires-Dist: jsonpath-ng (>=1.5.3,<2.0.0) ; extra == "opensearch"
Requires-Dist: modin (>=0.31,<0.33) ; extra == "modin"
Requires-Dist: numpy (>=1.26,<2.1.0) ; python_version < "3.10"
Requires-Dist: numpy (>=1.26,<3.0) ; python_version >= "3.10"
Requires-Dist: openpyxl (>=3.0.0,<4.0.0) ; extra == "openpyxl"
Requires-Dist: opensearch-py (>=2.0.0,<3.0.0) ; extra == "opensearch"
Requires-Dist: oracledb (>=1,<3) ; extra == "oracle"
Requires-Dist: packaging (>=21.1,<25.0)
Requires-Dist: pandas (>=1.2.0,<3.0.0)
Requires-Dist: pg8000 (>=1.29.0,<2.0.0) ; extra == "postgres"
Requires-Dist: progressbar2 (>=4.0.0,<5.0.0) ; extra == "progressbar"
Requires-Dist: pyarrow (>=18.0.0,<19.0.0) ; python_version >= "3.13"
Requires-Dist: pyarrow (>=8.0.0,<19.0.0) ; python_version < "3.13"
Requires-Dist: pymysql (>=1.0.0,<2.0.0) ; extra == "mysql"
Requires-Dist: pyodbc (>=4,<6) ; extra == "sqlserver"
Requires-Dist: ray[data,default] (>=2.30.0,<2.38.0) ; extra == "ray"
Requires-Dist: redshift-connector (>=2.0.0,<3.0.0) ; extra == "redshift"
Requires-Dist: requests (>=2.0.0,<3.0.0) ; extra == "gremlin" or extra == "sparql" or extra == "opencypher"
Requires-Dist: requests-aws4auth (>=1.1.1,<2.0.0) ; extra == "opensearch"
Requires-Dist: setuptools ; python_version >= "3.12"
Requires-Dist: typing-extensions (>=4.4.0,<5.0.0)
Project-URL: Documentation, https://aws-sdk-pandas.readthedocs.io/
Project-URL: Repository, https://github.com/aws/aws-sdk-pandas
